{"id":"https://medium.com/p/c9c3b11944fb","title":"Flipping a ‘False’ to ‘True’: The Google Bug That Paid Off","link":"https://medium.com/@hellother18/flipping-a-false-to-true-the-google-bug-that-paid-off-c9c3b11944fb?source=rss------bug_bounty-5","published":1716571539000,"description":"As a bug hunter, discovering a vulnerability that rewards you for your efforts is always thrilling. Recently, I discovered a fascinating&#x2026;Continue reading on Medium »","category":["penetration-testing","bugbounty-tips","bug-bounty","cybersecurity","hacker"],"pubDate":"Fri, 24 May 2024 17:25:39 GMT"}