{"id":"https://medium.com/p/d8509ef70436","title":"Breaking Business Logic — Part: 42–4= 2","link":"https://thehemdeep.medium.com/breaking-business-logic-part-42-4-2-d8509ef70436?source=rss------bug_bounty-5","published":1718300210000,"description":"Hello Hunters & Ninjas, Now I&#x2019;m back with my new write-up, First of all request to accept my apology friends for this too late write-up&#x2026;Continue reading on Medium »","category":["web-penetration-testing","web-security-testing","web-security","bug-bounty"],"pubDate":"Thu, 13 Jun 2024 17:36:50 GMT"}