{"id":"https://medium.com/p/3d29822c295d","title":"27.2 Lab: DOM XSS using web messages and a JavaScript URL","link":"https://cyberw1ng.medium.com/27-2-lab-dom-xss-using-web-messages-and-a-javascript-url-3d29822c295d?source=rss------bug_bounty-5","published":1717352013000,"description":"This lab demon strates a DOM-based redirection vulnerability that is triggered by web messaging. To solve this lab, construct an HTML page&#x2026;Continue reading on Medium »","category":["bug-bounty","cybersecurity","careers","hacking","penetration-testing"],"pubDate":"Sun, 02 Jun 2024 18:13:33 GMT"}